odoo/addons/web_tree_many2one_clickable/README.rst
odoo/addons/web_tree_many2one_clickable/__init__.py
odoo/addons/web_tree_many2one_clickable/__manifest__.py
odoo/addons/web_tree_many2one_clickable/static/description/icon.png
odoo/addons/web_tree_many2one_clickable/static/src/js/web_tree_many2one_clickable.js
odoo/addons/web_tree_many2one_clickable/static/src/xml/assets.xml
odoo11_addon_web_tree_many2one_clickable-11.0.1.0.1.dist-info/DESCRIPTION.rst
odoo11_addon_web_tree_many2one_clickable-11.0.1.0.1.dist-info/METADATA
odoo11_addon_web_tree_many2one_clickable-11.0.1.0.1.dist-info/RECORD
odoo11_addon_web_tree_many2one_clickable-11.0.1.0.1.dist-info/WHEEL
odoo11_addon_web_tree_many2one_clickable-11.0.1.0.1.dist-info/metadata.json
odoo11_addon_web_tree_many2one_clickable-11.0.1.0.1.dist-info/top_level.txt
